coloraiz/__init__.py
coloraiz-1.0.3.dist-info/LICENSE
coloraiz-1.0.3.dist-info/METADATA
coloraiz-1.0.3.dist-info/WHEEL
coloraiz-1.0.3.dist-info/top_level.txt
coloraiz-1.0.3.dist-info/RECORD
