Metadata-Version: 2.1
Name: coloraiz
Version: 1.0.3
Summary: Simple way to add color to your terminal text output
Home-page: https://github.com/morrrty/coloraiz
Author: Morty
Author-email: me@mortysmith.org
Project-URL: Bug Tracker, https://github.com/morrrty/coloraiz
Classifier: Programming Language :: Python :: 3
Classifier: License :: OSI Approved :: MIT License
Classifier: Operating System :: OS Independent
Requires-Python: >=3.6
License-File: LICENSE
Requires-Dist: colorama
Requires-Dist: requests
